__init__.py
accounting.py
budgeting.py
common.py
hello.py
main.py
pricing.py
quota.py
resources.py
user.py
lrzcc-0.8.0.dist-info/LICENSE
lrzcc-0.8.0.dist-info/METADATA
lrzcc-0.8.0.dist-info/WHEEL
lrzcc-0.8.0.dist-info/entry_points.txt
lrzcc-0.8.0.dist-info/top_level.txt
lrzcc-0.8.0.dist-info/RECORD
