Metadata-Version: 2.1
Name: lrzcc
Version: 0.8.0
Summary: Command line client for LRZ specific features of the Compute Cloud (cc.lrz.de).
Author-email: Sandro-Alessio Gierens <gierens@lrz.de>
Maintainer-email: Sandro-Alessio Gierens <gierens@lrz.de>, Niels Fallenbeck <fallenbeck@lrz.de>
License: MIT License
Project-URL: Homepage, https://github.com/LRZ-BADW/lrzcc/
Project-URL: Documentation, https://doku.lrz.de/compute-cloud-10333232.html
Project-URL: Repository, https://github.com/LRZ-BADW/lrzcc.git
Project-URL: Bug Tracker, https://github.com/LRZ-BADW/lrzcc/issues
Project-URL: Changelog, https://github.com/LRZ-BADW/lrzcc/blob/master/CHANGELOG.md
Keywords: lrz,cloud,compute cloud,api client,cli
Classifier: Development Status :: 5 - Production/Stable
Classifier: Intended Audience :: End Users/Desktop
Classifier: Topic :: Utilities
Classifier: License :: OSI Approved :: MIT License
Classifier: Programming Language :: Python
Requires-Python: >=3.8
License-File: LICENSE
Requires-Dist: argcomplete ==3.1.1
Requires-Dist: certifi ==2023.5.7
Requires-Dist: charset-normalizer ==3.2.0
Requires-Dist: idna ==3.4
Requires-Dist: requests ==2.31.0
Requires-Dist: tabulate ==0.9.0
Requires-Dist: urllib3 ==2.0.3
